README.md
setup.cfg
setup.py
textclf/__init__.py
textclf/main.py
textclf.egg-info/PKG-INFO
textclf.egg-info/SOURCES.txt
textclf.egg-info/dependency_links.txt
textclf.egg-info/entry_points.txt
textclf.egg-info/requires.txt
textclf.egg-info/top_level.txt
textclf/data/__init__.py
textclf/data/dictionary.py
textclf/data/loader.py
textclf/data/raw.py