Metadata-Version: 1.2
Name: textclf
Version: 0.1.0
Summary: 文本分类工具集
Home-page: UNKNOWN
Author: luopeixiang
Author-email: luopeixiang@qq.com
License: UNKNOWN
Platform: UNKNOWN
Requires-Python: >=3
